.DS_Store
alphapy/__init__.py
alphapy/__main__.py
alphapy/alias.py
alphapy/analysis.py
alphapy/calendrical.py
alphapy/data.py
alphapy/estimators.py
alphapy/features.py
alphapy/frame.py
alphapy/globals.py
alphapy/group.py
alphapy/market_flow.py
alphapy/market_variables.py
alphapy/model.py
alphapy/optimize.py
alphapy/plots.py
alphapy/portfolio.py
alphapy/space.py
alphapy/sport_flow.py
alphapy/system.py
alphapy/transforms.py
alphapy/utilities.py
alphapy/variables.py
alphapy-2.5.0.dist-info/LICENSE
alphapy-2.5.0.dist-info/METADATA
alphapy-2.5.0.dist-info/WHEEL
alphapy-2.5.0.dist-info/entry_points.txt
alphapy-2.5.0.dist-info/top_level.txt
alphapy-2.5.0.dist-info/RECORD
